player_salary_data/__init__.py
player_salary_data/data/player_salaries.xlsx
player_salary_data/player_data.py
player_salary_data-0.1.0.dist-info/METADATA
player_salary_data-0.1.0.dist-info/WHEEL
player_salary_data-0.1.0.dist-info/RECORD
